ls_vo.py
list_visible_only_dir_content-1.0.dist-info/LICENSE
list_visible_only_dir_content-1.0.dist-info/METADATA
list_visible_only_dir_content-1.0.dist-info/WHEEL
list_visible_only_dir_content-1.0.dist-info/top_level.txt
list_visible_only_dir_content-1.0.dist-info/RECORD
