Metadata-Version: 2.1
Name: list_visible_only_dir_content
Version: 1.0
Summary: lists visible only content of a given directory
Author: Mohamed Shalaby
Author-email: mshalaby@mail.com
Platform: Linix,Mac OS
Classifier: Programming Language :: Python :: 3
Classifier: Programming Language :: Python :: 3.6
Classifier: Programming Language :: Python :: 3.7
Classifier: Programming Language :: Python :: 3.10
Classifier: Operating System :: OS Independent
License-File: LICENSE
